iproov_portal_auth/__init__.py
iproov_portal_auth/auth.py
iproov_portal_auth/config.py
iproov_portal_auth/exceptions.py
iproov_portal_auth/token_cache.py
iproov_portal_auth-1.0.1.dist-info/METADATA
iproov_portal_auth-1.0.1.dist-info/WHEEL
iproov_portal_auth-1.0.1.dist-info/top_level.txt
iproov_portal_auth-1.0.1.dist-info/RECORD
