Metadata-Version: 2.4
Name: iproov-portal-auth
Version: 1.0.1
Summary: iProov Portal Authentication Library
Project-URL: Homepage, https://github.com/iproov/isoc-portal-login-services
Project-URL: Bug Tracker, https://github.com/iproov/isoc-portal-login-services/issues
Classifier: Development Status :: 5 - Production/Stable
Classifier: Intended Audience :: Developers
Classifier: License :: OSI Approved :: MIT License
Classifier: Operating System :: OS Independent
Classifier: Programming Language :: Python :: 3
Classifier: Programming Language :: Python :: 3.8
Classifier: Programming Language :: Python :: 3.9
Classifier: Programming Language :: Python :: 3.10
Classifier: Programming Language :: Python :: 3.11
Classifier: Programming Language :: Python :: 3.12
Requires-Python: >=3.8
Requires-Dist: google-auth>=1.35.0
Requires-Dist: google-api-core>=1.31.5
Requires-Dist: requests>=2.28.0
Requires-Dist: cryptography>=3.4.8
Provides-Extra: dev
Requires-Dist: pytest>=7.0.0; extra == "dev"
Requires-Dist: pytest-cov>=4.0.0; extra == "dev"
Requires-Dist: black>=22.0.0; extra == "dev"
Requires-Dist: flake8>=5.0.0; extra == "dev"
Requires-Dist: mypy>=1.0.0; extra == "dev"
Requires-Dist: types-requests>=2.28.0; extra == "dev"
